upscaler/__init__.py
upscaler/server.py
upscaler/models/__init__.py
upscaler/models/esrgan/__init__.py
upscaler/models/esrgan/modelling_esrgan.py
upscaler/models/esrgan/modelling_esrgan_utils.py
upscaler-0.0.6.dist-info/METADATA
upscaler-0.0.6.dist-info/WHEEL
upscaler-0.0.6.dist-info/top_level.txt
upscaler-0.0.6.dist-info/RECORD
