Metadata-Version: 2.1
Name: upscaler
Version: 0.0.6
Summary: Let's upscale!
Home-page: https://github.com/Morphogens/upscaler
Author: Morphogen
Author-email: vipermu97@gmail.com
License: UNKNOWN
Platform: UNKNOWN
Classifier: Programming Language :: Python :: 3
Classifier: License :: OSI Approved :: MIT License
Classifier: Operating System :: OS Independent
Requires-Python: >=3.7
Requires-Dist: torch (==1.7.1)
Requires-Dist: pillow (==8.4.0)
Requires-Dist: torchvision (==0.8.2)
Requires-Dist: tqdm (==4.62.3)
